tap_getstat/__init__.py
tap_getstat/schemas/keywords.json
tap_getstat/schemas/projects.json
tap_getstat/schemas/rankings.json
tap_getstat/schemas/sites.json
tap_getstat/schemas/sov.json
tap_getstat/schemas/tags.json
tap_getstat-1.1.1.dist-info/LICENSE
tap_getstat-1.1.1.dist-info/METADATA
tap_getstat-1.1.1.dist-info/WHEEL
tap_getstat-1.1.1.dist-info/entry_points.txt
tap_getstat-1.1.1.dist-info/top_level.txt
tap_getstat-1.1.1.dist-info/RECORD
