Metadata-Version: 2.1
Name: tap-getstat
Version: 1.1.1
Summary: Singer.io tap for extracting data from the getstat.com API
Home-page: https://singer.io
Author: Nick Hassell
Author-email: UNKNOWN
License: UNKNOWN
Platform: UNKNOWN
Classifier: Programming Language :: Python :: 3 :: Only
Requires-Dist: singer-python
Requires-Dist: requests
Requires-Dist: backoff (==1.3.2)
